{
    "openapi": "3.0.0",
    "info": {
        "title": "Your API Title",
        "description": "Your API Description",
        "version": "1.0.0"
    },
    "security": [
        {
            "BearerAuth": []
        }
    ],
    "components": {
        "securitySchemes": {
            "BearerAuth": {
                "type": "http",
                "scheme": "bearer",
                "bearerFormat": "JWT"
            }
        }
    },
    "consumes": [
        "multipart/form-data"
    ],
    "paths": {
        "/api/email/paiement/1": {
            "post": {
                "summary": "CommandePayee",
                "description": "",
                "responses": {
                    "201": {
                        "description": "Created successfully",
                        "content": {
                            "application/json": {
                                "schema": {},
                                "example": ""
                            }
                        }
                    },
                    "400": {
                        "description": "Bad Request",
                        "content": {
                            "application/json": {
                                "schema": {},
                                "example": ""
                            }
                        }
                    },
                    "401": {
                        "description": "Unauthorized",
                        "content": {
                            "application/json": {
                                "schema": {},
                                "example": ""
                            }
                        }
                    },
                    "403": {
                        "description": "Forbidden",
                        "content": {
                            "application/json": {
                                "schema": {},
                                "example": ""
                            }
                        }
                    }
                },
                "tags": [
                    "Email"
                ],
                "parameters": [
                    {
                        "in": "header",
                        "name": "User-Agent",
                        "type": "string"
                    }
                ],
                "requestBody": {
                    "content": {
                        "multipart/form-data": {
                            "schema": {
                                "type": "object",
                                "properties": {
                                    "ligneCommande": {
                                        "type": "string",
                                        "format": "binary"
                                    }
                                }
                            },
                            "example": {
                                "ligneCommande": {
                                    "email": "client@example.com",
                                    "produitBoutique": {
                                        "nom": "Nom du Produit"
                                    },
                                    "quantite_totale": 1,
                                    "prix_totale": 100
                                }
                            }
                        }
                    }
                }
            }
        },
        "/api/email/commande/1": {
            "get": {
                "summary": "CommandeConfirmee",
                "description": "",
                "responses": {
                    "200": {
                        "description": "OK",
                        "content": {
                            "application/json": {
                                "schema": {},
                                "example": ""
                            }
                        }
                    },
                    "404": {
                        "description": "Not Found",
                        "content": {
                            "application/json": {
                                "schema": {},
                                "example": ""
                            }
                        }
                    },
                    "500": {
                        "description": "Internal Server Error",
                        "content": {
                            "application/json": {
                                "schema": {},
                                "example": ""
                            }
                        }
                    }
                },
                "tags": [
                    "Email"
                ],
                "parameters": [
                    {
                        "in": "header",
                        "name": "User-Agent",
                        "type": "string"
                    }
                ],
                "requestBody": {
                    "content": {
                        "multipart/form-data": {
                            "schema": {
                                "type": "object",
                                "properties": {
                                    "ligneCommande": {
                                        "type": "string",
                                        "format": "binary"
                                    }
                                }
                            },
                            "example": {
                                "ligneCommande": {
                                    "email": "client@example.com",
                                    "produitBoutique": {
                                        "nom": "Nom du Produit"
                                    },
                                    "quantite_totale": 1,
                                    "prix_totale": 100
                                }
                            }
                        }
                    }
                }
            }
        },
        "/api/lignes_commandes": {
            "get": {
                "summary": "Afficher la liste",
                "description": "",
                "responses": {
                    "200": {
                        "description": "OK",
                        "content": {
                            "application/json": {
                                "schema": {},
                                "example": ""
                            }
                        }
                    },
                    "404": {
                        "description": "Not Found",
                        "content": {
                            "application/json": {
                                "schema": {},
                                "example": ""
                            }
                        }
                    },
                    "500": {
                        "description": "Internal Server Error",
                        "content": {
                            "application/json": {
                                "schema": {},
                                "example": ""
                            }
                        }
                    }
                },
                "tags": [
                    "Gestion ligne_commandes (Panier)"
                ],
                "parameters": [
                    {
                        "in": "header",
                        "name": "User-Agent",
                        "type": "string"
                    }
                ]
            },
            "post": {
                "summary": "Ajouter",
                "description": "",
                "responses": {
                    "201": {
                        "description": "Created successfully",
                        "content": {
                            "application/json": {
                                "schema": {},
                                "example": ""
                            }
                        }
                    },
                    "400": {
                        "description": "Bad Request",
                        "content": {
                            "application/json": {
                                "schema": {},
                                "example": ""
                            }
                        }
                    },
                    "401": {
                        "description": "Unauthorized",
                        "content": {
                            "application/json": {
                                "schema": {},
                                "example": ""
                            }
                        }
                    },
                    "403": {
                        "description": "Forbidden",
                        "content": {
                            "application/json": {
                                "schema": {},
                                "example": ""
                            }
                        }
                    }
                },
                "tags": [
                    "Gestion ligne_commandes (Panier)"
                ],
                "parameters": [
                    {
                        "in": "header",
                        "name": "User-Agent",
                        "type": "string"
                    }
                ],
                "requestBody": {
                    "content": {
                        "multipart/form-data": {
                            "schema": {
                                "type": "object",
                                "properties": {
                                    "produit_boutique_id": {
                                        "type": "integer"
                                    },
                                    "quantite_totale": {
                                        "type": "integer"
                                    },
                                    "prix_totale": {
                                        "type": "integer"
                                    }
                                }
                            },
                            "example": {
                                "produit_boutique_id": 1,
                                "quantite_totale": 8,
                                "prix_totale": 10.99
                            }
                        }
                    }
                }
            }
        },
        "/api/lignes_commandes/13": {
            "get": {
                "summary": "Voir detail",
                "description": "",
                "responses": {
                    "200": {
                        "description": "OK",
                        "content": {
                            "application/json": {
                                "schema": {},
                                "example": ""
                            }
                        }
                    },
                    "404": {
                        "description": "Not Found",
                        "content": {
                            "application/json": {
                                "schema": {},
                                "example": ""
                            }
                        }
                    },
                    "500": {
                        "description": "Internal Server Error",
                        "content": {
                            "application/json": {
                                "schema": {},
                                "example": ""
                            }
                        }
                    }
                },
                "tags": [
                    "Gestion ligne_commandes (Panier)"
                ],
                "parameters": [
                    {
                        "in": "header",
                        "name": "User-Agent",
                        "type": "string"
                    }
                ]
            },
            "put": {
                "summary": "Modifier",
                "description": "",
                "responses": {
                    "200": {
                        "description": "OK",
                        "content": {
                            "application/json": {
                                "schema": {},
                                "example": ""
                            }
                        }
                    },
                    "404": {
                        "description": "Not Found",
                        "content": {
                            "application/json": {
                                "schema": {},
                                "example": ""
                            }
                        }
                    },
                    "500": {
                        "description": "Internal Server Error",
                        "content": {
                            "application/json": {
                                "schema": {},
                                "example": ""
                            }
                        }
                    }
                },
                "tags": [
                    "Gestion ligne_commandes (Panier)"
                ],
                "parameters": [
                    {
                        "in": "header",
                        "name": "User-Agent",
                        "type": "string"
                    }
                ],
                "requestBody": {
                    "content": {
                        "application/x-www-form-urlencoded": {
                            "schema": {
                                "type": "object",
                                "properties": {
                                    "produit_boutique_id": {
                                        "type": "integer"
                                    },
                                    "date": {
                                        "type": "string"
                                    },
                                    "statut": {
                                        "type": "string"
                                    },
                                    "quantite_totale": {
                                        "type": "integer"
                                    },
                                    "prix_totale": {
                                        "type": "integer"
                                    }
                                }
                            },
                            "example": {
                                "produit_boutique_id": 9,
                                "date": "2024-09-23",
                                "statut": "en attente",
                                "quantite_totale": 590,
                                "prix_totale": 100.99
                            }
                        }
                    }
                }
            }
        },
        "/api/lignes_commandes/16": {
            "delete": {
                "summary": "Supprimer",
                "description": "",
                "responses": {
                    "204": {
                        "description": "Deleted successfully",
                        "content": {
                            "application/json": {
                                "schema": {},
                                "example": ""
                            }
                        }
                    },
                    "401": {
                        "description": "Unauthorized",
                        "content": {
                            "application/json": {
                                "schema": {},
                                "example": ""
                            }
                        }
                    },
                    "403": {
                        "description": "Forbidden",
                        "content": {
                            "application/json": {
                                "schema": {},
                                "example": ""
                            }
                        }
                    },
                    "404": {
                        "description": "Not Found",
                        "content": {
                            "application/json": {
                                "schema": {},
                                "example": ""
                            }
                        }
                    }
                },
                "tags": [
                    "Gestion ligne_commandes (Panier)"
                ],
                "parameters": [
                    {
                        "in": "header",
                        "name": "User-Agent",
                        "type": "string"
                    }
                ]
            }
        },
        "/api/produitBoutique": {
            "get": {
                "summary": "Afficher la liste",
                "description": "",
                "responses": {
                    "200": {
                        "description": "OK",
                        "content": {
                            "application/json": {
                                "schema": {},
                                "example": ""
                            }
                        }
                    },
                    "404": {
                        "description": "Not Found",
                        "content": {
                            "application/json": {
                                "schema": {},
                                "example": ""
                            }
                        }
                    },
                    "500": {
                        "description": "Internal Server Error",
                        "content": {
                            "application/json": {
                                "schema": {},
                                "example": ""
                            }
                        }
                    }
                },
                "tags": [
                    "Gestion des produits_boutiques"
                ],
                "parameters": [
                    {
                        "in": "header",
                        "name": "User-Agent",
                        "type": "string"
                    }
                ]
            },
            "post": {
                "summary": "Ajouter",
                "description": "",
                "responses": {
                    "201": {
                        "description": "Created successfully",
                        "content": {
                            "application/json": {
                                "schema": {},
                                "example": ""
                            }
                        }
                    },
                    "400": {
                        "description": "Bad Request",
                        "content": {
                            "application/json": {
                                "schema": {},
                                "example": ""
                            }
                        }
                    },
                    "401": {
                        "description": "Unauthorized",
                        "content": {
                            "application/json": {
                                "schema": {},
                                "example": ""
                            }
                        }
                    },
                    "403": {
                        "description": "Forbidden",
                        "content": {
                            "application/json": {
                                "schema": {},
                                "example": ""
                            }
                        }
                    }
                },
                "tags": [
                    "Gestion des produits_boutiques"
                ],
                "parameters": [
                    {
                        "in": "header",
                        "name": "User-Agent",
                        "type": "string"
                    }
                ],
                "requestBody": {
                    "content": {
                        "multipart/form-data": {
                            "schema": {
                                "type": "object",
                                "properties": {
                                    "produit_id": {
                                        "type": "integer"
                                    },
                                    "boutique_id": {
                                        "type": "integer"
                                    },
                                    "quantite": {
                                        "type": "integer"
                                    }
                                }
                            },
                            "example": {
                                "produit_id": 1,
                                "boutique_id": 4,
                                "quantite": 760
                            }
                        }
                    }
                }
            }
        },
        "/api/produitBoutique/2": {
            "get": {
                "summary": "Voir detail",
                "description": "",
                "responses": {
                    "200": {
                        "description": "OK",
                        "content": {
                            "application/json": {
                                "schema": {},
                                "example": ""
                            }
                        }
                    },
                    "404": {
                        "description": "Not Found",
                        "content": {
                            "application/json": {
                                "schema": {},
                                "example": ""
                            }
                        }
                    },
                    "500": {
                        "description": "Internal Server Error",
                        "content": {
                            "application/json": {
                                "schema": {},
                                "example": ""
                            }
                        }
                    }
                },
                "tags": [
                    "Gestion des produits_boutiques"
                ],
                "parameters": [
                    {
                        "in": "header",
                        "name": "User-Agent",
                        "type": "string"
                    }
                ]
            },
            "put": {
                "summary": "Modifier",
                "description": "",
                "responses": {
                    "200": {
                        "description": "OK",
                        "content": {
                            "application/json": {
                                "schema": {},
                                "example": ""
                            }
                        }
                    },
                    "404": {
                        "description": "Not Found",
                        "content": {
                            "application/json": {
                                "schema": {},
                                "example": ""
                            }
                        }
                    },
                    "500": {
                        "description": "Internal Server Error",
                        "content": {
                            "application/json": {
                                "schema": {},
                                "example": ""
                            }
                        }
                    }
                },
                "tags": [
                    "Gestion des produits_boutiques"
                ],
                "parameters": [
                    {
                        "in": "header",
                        "name": "User-Agent",
                        "type": "string"
                    }
                ],
                "requestBody": {
                    "content": {
                        "application/x-www-form-urlencoded": {
                            "schema": {
                                "type": "object",
                                "properties": {
                                    "produit_id": {
                                        "type": "integer"
                                    },
                                    "boutique_id": {
                                        "type": "integer"
                                    },
                                    "quantite": {
                                        "type": "integer"
                                    }
                                }
                            },
                            "example": {
                                "produit_id": 1,
                                "boutique_id": 4,
                                "quantite": 10
                            }
                        }
                    }
                }
            }
        },
        "/api/produitBoutique/5": {
            "delete": {
                "summary": "Supprimer",
                "description": "",
                "responses": {
                    "204": {
                        "description": "Deleted successfully",
                        "content": {
                            "application/json": {
                                "schema": {},
                                "example": ""
                            }
                        }
                    },
                    "401": {
                        "description": "Unauthorized",
                        "content": {
                            "application/json": {
                                "schema": {},
                                "example": ""
                            }
                        }
                    },
                    "403": {
                        "description": "Forbidden",
                        "content": {
                            "application/json": {
                                "schema": {},
                                "example": ""
                            }
                        }
                    },
                    "404": {
                        "description": "Not Found",
                        "content": {
                            "application/json": {
                                "schema": {},
                                "example": ""
                            }
                        }
                    }
                },
                "tags": [
                    "Gestion des produits_boutiques"
                ],
                "parameters": [
                    {
                        "in": "header",
                        "name": "User-Agent",
                        "type": "string"
                    }
                ]
            }
        },
        "/api/regions": {
            "get": {
                "summary": "Afficher la liste",
                "description": "",
                "responses": {
                    "200": {
                        "description": "OK",
                        "content": {
                            "application/json": {
                                "schema": {},
                                "example": ""
                            }
                        }
                    },
                    "404": {
                        "description": "Not Found",
                        "content": {
                            "application/json": {
                                "schema": {},
                                "example": ""
                            }
                        }
                    },
                    "500": {
                        "description": "Internal Server Error",
                        "content": {
                            "application/json": {
                                "schema": {},
                                "example": ""
                            }
                        }
                    }
                },
                "tags": [
                    "Gestion des regions"
                ],
                "parameters": [
                    {
                        "in": "header",
                        "name": "User-Agent",
                        "type": "string"
                    }
                ]
            },
            "post": {
                "summary": "Ajouter",
                "description": "",
                "responses": {
                    "201": {
                        "description": "Created successfully",
                        "content": {
                            "application/json": {
                                "schema": {},
                                "example": ""
                            }
                        }
                    },
                    "400": {
                        "description": "Bad Request",
                        "content": {
                            "application/json": {
                                "schema": {},
                                "example": ""
                            }
                        }
                    },
                    "401": {
                        "description": "Unauthorized",
                        "content": {
                            "application/json": {
                                "schema": {},
                                "example": ""
                            }
                        }
                    },
                    "403": {
                        "description": "Forbidden",
                        "content": {
                            "application/json": {
                                "schema": {},
                                "example": ""
                            }
                        }
                    }
                },
                "tags": [
                    "Gestion des regions"
                ],
                "parameters": [
                    {
                        "in": "header",
                        "name": "User-Agent",
                        "type": "string"
                    }
                ],
                "requestBody": {
                    "content": {
                        "multipart/form-data": {
                            "schema": {
                                "type": "object",
                                "properties": {
                                    "nom": {
                                        "type": "string"
                                    }
                                }
                            },
                            "example": {
                                "nom": "Fatick"
                            }
                        }
                    }
                }
            }
        },
        "/api/regions/8": {
            "get": {
                "summary": "Voir detail",
                "description": "",
                "responses": {
                    "200": {
                        "description": "OK",
                        "content": {
                            "application/json": {
                                "schema": {},
                                "example": ""
                            }
                        }
                    },
                    "404": {
                        "description": "Not Found",
                        "content": {
                            "application/json": {
                                "schema": {},
                                "example": ""
                            }
                        }
                    },
                    "500": {
                        "description": "Internal Server Error",
                        "content": {
                            "application/json": {
                                "schema": {},
                                "example": ""
                            }
                        }
                    }
                },
                "tags": [
                    "Gestion des regions"
                ],
                "parameters": [
                    {
                        "in": "header",
                        "name": "User-Agent",
                        "type": "string"
                    }
                ]
            }
        },
        "/api/regions/3": {
            "delete": {
                "summary": "Supprimer",
                "description": "",
                "responses": {
                    "204": {
                        "description": "Deleted successfully",
                        "content": {
                            "application/json": {
                                "schema": {},
                                "example": ""
                            }
                        }
                    },
                    "401": {
                        "description": "Unauthorized",
                        "content": {
                            "application/json": {
                                "schema": {},
                                "example": ""
                            }
                        }
                    },
                    "403": {
                        "description": "Forbidden",
                        "content": {
                            "application/json": {
                                "schema": {},
                                "example": ""
                            }
                        }
                    },
                    "404": {
                        "description": "Not Found",
                        "content": {
                            "application/json": {
                                "schema": {},
                                "example": ""
                            }
                        }
                    }
                },
                "tags": [
                    "Gestion des regions"
                ],
                "parameters": [
                    {
                        "in": "header",
                        "name": "User-Agent",
                        "type": "string"
                    }
                ]
            }
        },
        "/api/regions/11": {
            "put": {
                "summary": "Modifier",
                "description": "",
                "responses": {
                    "200": {
                        "description": "OK",
                        "content": {
                            "application/json": {
                                "schema": {},
                                "example": ""
                            }
                        }
                    },
                    "404": {
                        "description": "Not Found",
                        "content": {
                            "application/json": {
                                "schema": {},
                                "example": ""
                            }
                        }
                    },
                    "500": {
                        "description": "Internal Server Error",
                        "content": {
                            "application/json": {
                                "schema": {},
                                "example": ""
                            }
                        }
                    }
                },
                "tags": [
                    "Gestion des regions"
                ],
                "parameters": [
                    {
                        "in": "header",
                        "name": "User-Agent",
                        "type": "string"
                    }
                ],
                "requestBody": {
                    "content": {
                        "application/x-www-form-urlencoded": {
                            "schema": {
                                "type": "object",
                                "properties": {
                                    "nom": {
                                        "type": "string"
                                    }
                                }
                            },
                            "example": {
                                "nom": "Dioubel"
                            }
                        }
                    }
                }
            }
        },
        "/api/notifications": {
            "get": {
                "summary": "Afficher la liste",
                "description": "",
                "responses": {
                    "200": {
                        "description": "OK",
                        "content": {
                            "application/json": {
                                "schema": {},
                                "example": ""
                            }
                        }
                    },
                    "404": {
                        "description": "Not Found",
                        "content": {
                            "application/json": {
                                "schema": {},
                                "example": ""
                            }
                        }
                    },
                    "500": {
                        "description": "Internal Server Error",
                        "content": {
                            "application/json": {
                                "schema": {},
                                "example": ""
                            }
                        }
                    }
                },
                "tags": [
                    "Gestion des notifications"
                ],
                "parameters": [
                    {
                        "in": "header",
                        "name": "User-Agent",
                        "type": "string"
                    }
                ]
            },
            "post": {
                "summary": "Ajouter",
                "description": "",
                "responses": {
                    "201": {
                        "description": "Created successfully",
                        "content": {
                            "application/json": {
                                "schema": {},
                                "example": ""
                            }
                        }
                    },
                    "400": {
                        "description": "Bad Request",
                        "content": {
                            "application/json": {
                                "schema": {},
                                "example": ""
                            }
                        }
                    },
                    "401": {
                        "description": "Unauthorized",
                        "content": {
                            "application/json": {
                                "schema": {},
                                "example": ""
                            }
                        }
                    },
                    "403": {
                        "description": "Forbidden",
                        "content": {
                            "application/json": {
                                "schema": {},
                                "example": ""
                            }
                        }
                    }
                },
                "tags": [
                    "Gestion des notifications"
                ],
                "parameters": [
                    {
                        "in": "header",
                        "name": "User-Agent",
                        "type": "string"
                    }
                ],
                "requestBody": {
                    "content": {
                        "multipart/form-data": {
                            "schema": {
                                "type": "object",
                                "properties": {
                                    "user_id": {
                                        "type": "integer"
                                    },
                                    "objet": {
                                        "type": "string"
                                    },
                                    "description": {
                                        "type": "string"
                                    }
                                }
                            },
                            "example": {
                                "user_id": 3,
                                "objet": "Nouvelle notification",
                                "description": "Ceci est une notification."
                            }
                        }
                    }
                }
            }
        },
        "/api/notifications/2": {
            "get": {
                "summary": "Voir detail",
                "description": "",
                "responses": {
                    "200": {
                        "description": "OK",
                        "content": {
                            "application/json": {
                                "schema": {},
                                "example": ""
                            }
                        }
                    },
                    "404": {
                        "description": "Not Found",
                        "content": {
                            "application/json": {
                                "schema": {},
                                "example": ""
                            }
                        }
                    },
                    "500": {
                        "description": "Internal Server Error",
                        "content": {
                            "application/json": {
                                "schema": {},
                                "example": ""
                            }
                        }
                    }
                },
                "tags": [
                    "Gestion des notifications"
                ],
                "parameters": [
                    {
                        "in": "header",
                        "name": "User-Agent",
                        "type": "string"
                    }
                ]
            }
        },
        "/api/notifications/3": {
            "delete": {
                "summary": "Suppprimer",
                "description": "",
                "responses": {
                    "204": {
                        "description": "Deleted successfully",
                        "content": {
                            "application/json": {
                                "schema": {},
                                "example": ""
                            }
                        }
                    },
                    "401": {
                        "description": "Unauthorized",
                        "content": {
                            "application/json": {
                                "schema": {},
                                "example": ""
                            }
                        }
                    },
                    "403": {
                        "description": "Forbidden",
                        "content": {
                            "application/json": {
                                "schema": {},
                                "example": ""
                            }
                        }
                    },
                    "404": {
                        "description": "Not Found",
                        "content": {
                            "application/json": {
                                "schema": {},
                                "example": ""
                            }
                        }
                    }
                },
                "tags": [
                    "Gestion des notifications"
                ],
                "parameters": [
                    {
                        "in": "header",
                        "name": "User-Agent",
                        "type": "string"
                    }
                ]
            }
        },
        "/api/notifications/1": {
            "put": {
                "summary": "Modifier",
                "description": "",
                "responses": {
                    "200": {
                        "description": "OK",
                        "content": {
                            "application/json": {
                                "schema": {},
                                "example": ""
                            }
                        }
                    },
                    "404": {
                        "description": "Not Found",
                        "content": {
                            "application/json": {
                                "schema": {},
                                "example": ""
                            }
                        }
                    },
                    "500": {
                        "description": "Internal Server Error",
                        "content": {
                            "application/json": {
                                "schema": {},
                                "example": ""
                            }
                        }
                    }
                },
                "tags": [
                    "Gestion des notifications"
                ],
                "parameters": [
                    {
                        "in": "header",
                        "name": "User-Agent",
                        "type": "string"
                    }
                ],
                "requestBody": {
                    "content": {
                        "application/x-www-form-urlencoded": {
                            "schema": {
                                "type": "object",
                                "properties": {
                                    "user_id": {
                                        "type": "integer"
                                    },
                                    "objet": {
                                        "type": "string"
                                    },
                                    "description": {
                                        "type": "string"
                                    }
                                }
                            },
                            "example": {
                                "user_id": 1,
                                "objet": "Payement effectuer avec succes",
                                "description": "Ceci est une notification."
                            }
                        }
                    }
                }
            }
        },
        "/api/boutiques": {
            "get": {
                "summary": "Afficher la liste",
                "description": "",
                "responses": {
                    "200": {
                        "description": "OK",
                        "content": {
                            "application/json": {
                                "schema": {},
                                "example": ""
                            }
                        }
                    },
                    "404": {
                        "description": "Not Found",
                        "content": {
                            "application/json": {
                                "schema": {},
                                "example": ""
                            }
                        }
                    },
                    "500": {
                        "description": "Internal Server Error",
                        "content": {
                            "application/json": {
                                "schema": {},
                                "example": ""
                            }
                        }
                    }
                },
                "tags": [
                    "Gestion des boutiques"
                ],
                "parameters": [
                    {
                        "in": "header",
                        "name": "User-Agent",
                        "type": "string"
                    }
                ]
            },
            "post": {
                "summary": "Ajouter",
                "description": "",
                "responses": {
                    "201": {
                        "description": "Created successfully",
                        "content": {
                            "application/json": {
                                "schema": {},
                                "example": ""
                            }
                        }
                    },
                    "400": {
                        "description": "Bad Request",
                        "content": {
                            "application/json": {
                                "schema": {},
                                "example": ""
                            }
                        }
                    },
                    "401": {
                        "description": "Unauthorized",
                        "content": {
                            "application/json": {
                                "schema": {},
                                "example": ""
                            }
                        }
                    },
                    "403": {
                        "description": "Forbidden",
                        "content": {
                            "application/json": {
                                "schema": {},
                                "example": ""
                            }
                        }
                    }
                },
                "tags": [
                    "Gestion des boutiques"
                ],
                "parameters": [
                    {
                        "in": "header",
                        "name": "User-Agent",
                        "type": "string"
                    }
                ],
                "requestBody": {
                    "content": {
                        "multipart/form-data": {
                            "schema": {
                                "type": "object",
                                "properties": {
                                    "nom": {
                                        "type": "string"
                                    },
                                    "adresse": {
                                        "type": "string"
                                    },
                                    "telephone": {
                                        "type": "string"
                                    },
                                    "region_id": {
                                        "type": "integer"
                                    }
                                }
                            },
                            "example": {
                                "nom": "Ferlo-kosamnay",
                                "adresse": "124 Rue gou",
                                "telephone": "771065156",
                                "region_id": 1
                            }
                        }
                    }
                }
            }
        },
        "/api/boutiques/1": {
            "get": {
                "summary": "Voir detail",
                "description": "",
                "responses": {
                    "200": {
                        "description": "OK",
                        "content": {
                            "application/json": {
                                "schema": {},
                                "example": ""
                            }
                        }
                    },
                    "404": {
                        "description": "Not Found",
                        "content": {
                            "application/json": {
                                "schema": {},
                                "example": ""
                            }
                        }
                    },
                    "500": {
                        "description": "Internal Server Error",
                        "content": {
                            "application/json": {
                                "schema": {},
                                "example": ""
                            }
                        }
                    }
                },
                "tags": [
                    "Gestion des boutiques"
                ],
                "parameters": [
                    {
                        "in": "header",
                        "name": "User-Agent",
                        "type": "string"
                    }
                ]
            }
        },
        "/api/boutiques/5": {
            "delete": {
                "summary": "Supprimer",
                "description": "",
                "responses": {
                    "204": {
                        "description": "Deleted successfully",
                        "content": {
                            "application/json": {
                                "schema": {},
                                "example": ""
                            }
                        }
                    },
                    "401": {
                        "description": "Unauthorized",
                        "content": {
                            "application/json": {
                                "schema": {},
                                "example": ""
                            }
                        }
                    },
                    "403": {
                        "description": "Forbidden",
                        "content": {
                            "application/json": {
                                "schema": {},
                                "example": ""
                            }
                        }
                    },
                    "404": {
                        "description": "Not Found",
                        "content": {
                            "application/json": {
                                "schema": {},
                                "example": ""
                            }
                        }
                    }
                },
                "tags": [
                    "Gestion des boutiques"
                ],
                "parameters": [
                    {
                        "in": "header",
                        "name": "User-Agent",
                        "type": "string"
                    }
                ]
            }
        },
        "/api/boutiques/4": {
            "put": {
                "summary": "Modifier",
                "description": "",
                "responses": {
                    "200": {
                        "description": "OK",
                        "content": {
                            "application/json": {
                                "schema": {},
                                "example": ""
                            }
                        }
                    },
                    "404": {
                        "description": "Not Found",
                        "content": {
                            "application/json": {
                                "schema": {},
                                "example": ""
                            }
                        }
                    },
                    "500": {
                        "description": "Internal Server Error",
                        "content": {
                            "application/json": {
                                "schema": {},
                                "example": ""
                            }
                        }
                    }
                },
                "tags": [
                    "Gestion des boutiques"
                ],
                "parameters": [
                    {
                        "in": "header",
                        "name": "User-Agent",
                        "type": "string"
                    }
                ],
                "requestBody": {
                    "content": {
                        "application/x-www-form-urlencoded": {
                            "schema": {
                                "type": "object",
                                "properties": {
                                    "nom": {
                                        "type": "string"
                                    },
                                    "adresse": {
                                        "type": "string"
                                    },
                                    "telephone": {
                                        "type": "string"
                                    },
                                    "region_id": {
                                        "type": "integer"
                                    }
                                }
                            },
                            "example": {
                                "nom": "Ferlo-kosamnay",
                                "adresse": "124 Rue goutes",
                                "telephone": "771065156",
                                "region_id": 1
                            }
                        }
                    }
                }
            }
        },
        "/api/produits": {
            "get": {
                "summary": "Afficher la liste ",
                "description": "",
                "responses": {
                    "200": {
                        "description": "OK",
                        "content": {
                            "application/json": {
                                "schema": {},
                                "example": ""
                            }
                        }
                    },
                    "404": {
                        "description": "Not Found",
                        "content": {
                            "application/json": {
                                "schema": {},
                                "example": ""
                            }
                        }
                    },
                    "500": {
                        "description": "Internal Server Error",
                        "content": {
                            "application/json": {
                                "schema": {},
                                "example": ""
                            }
                        }
                    }
                },
                "tags": [
                    "Gestion des produits"
                ],
                "parameters": [
                    {
                        "in": "header",
                        "name": "User-Agent",
                        "type": "string"
                    }
                ]
            },
            "post": {
                "summary": "Ajouter",
                "description": "",
                "responses": {
                    "201": {
                        "description": "Created successfully",
                        "content": {
                            "application/json": {
                                "schema": {},
                                "example": ""
                            }
                        }
                    },
                    "400": {
                        "description": "Bad Request",
                        "content": {
                            "application/json": {
                                "schema": {},
                                "example": ""
                            }
                        }
                    },
                    "401": {
                        "description": "Unauthorized",
                        "content": {
                            "application/json": {
                                "schema": {},
                                "example": ""
                            }
                        }
                    },
                    "403": {
                        "description": "Forbidden",
                        "content": {
                            "application/json": {
                                "schema": {},
                                "example": ""
                            }
                        }
                    }
                },
                "tags": [
                    "Gestion des produits"
                ],
                "parameters": [
                    {
                        "in": "path",
                        "name": "image",
                        "type": "text"
                    },
                    {
                        "in": "path",
                        "name": "nom",
                        "type": "string"
                    },
                    {
                        "in": "path",
                        "name": "description",
                        "type": "string"
                    },
                    {
                        "in": "path",
                        "name": "prix",
                        "type": "string"
                    },
                    {
                        "in": "path",
                        "name": "quantite",
                        "type": "string"
                    },
                    {
                        "in": "header",
                        "name": "User-Agent",
                        "type": "string"
                    }
                ],
                "requestBody": {
                    "content": {
                        "multipart/form-data": {
                            "schema": {
                                "type": "object",
                                "properties": {
                                    "categorie_id": {
                                        "type": "integer"
                                    },
                                    "image": {
                                        "type": "string"
                                    },
                                    "description": {
                                        "type": "string"
                                    },
                                    "prix": {
                                        "type": "integer"
                                    },
                                    "quantite": {
                                        "type": "integer"
                                    },
                                    "reference": {
                                        "type": "string"
                                    }
                                }
                            },
                            "example": {
                                "categorie_id": 2,
                                "image": "chemin/vers/image.jpg",
                                "description": "Description tomate",
                                "prix": 19.99,
                                "quantite": 50,
                                "reference": "PROD12349"
                            }
                        }
                    }
                }
            }
        },
        "/api/produits/1": {
            "get": {
                "summary": "Voir detail",
                "description": "",
                "responses": {
                    "200": {
                        "description": "OK",
                        "content": {
                            "application/json": {
                                "schema": {},
                                "example": ""
                            }
                        }
                    },
                    "404": {
                        "description": "Not Found",
                        "content": {
                            "application/json": {
                                "schema": {},
                                "example": ""
                            }
                        }
                    },
                    "500": {
                        "description": "Internal Server Error",
                        "content": {
                            "application/json": {
                                "schema": {},
                                "example": ""
                            }
                        }
                    }
                },
                "tags": [
                    "Gestion des produits"
                ],
                "parameters": [
                    {
                        "in": "header",
                        "name": "User-Agent",
                        "type": "string"
                    }
                ]
            }
        },
        "/api/produits/3": {
            "delete": {
                "summary": "Supprimer",
                "description": "",
                "responses": {
                    "204": {
                        "description": "Deleted successfully",
                        "content": {
                            "application/json": {
                                "schema": {},
                                "example": ""
                            }
                        }
                    },
                    "401": {
                        "description": "Unauthorized",
                        "content": {
                            "application/json": {
                                "schema": {},
                                "example": ""
                            }
                        }
                    },
                    "403": {
                        "description": "Forbidden",
                        "content": {
                            "application/json": {
                                "schema": {},
                                "example": ""
                            }
                        }
                    },
                    "404": {
                        "description": "Not Found",
                        "content": {
                            "application/json": {
                                "schema": {},
                                "example": ""
                            }
                        }
                    }
                },
                "tags": [
                    "Gestion des produits"
                ],
                "parameters": [
                    {
                        "in": "header",
                        "name": "User-Agent",
                        "type": "string"
                    }
                ]
            }
        },
        "/api/produits/5": {
            "put": {
                "summary": "Modifier",
                "description": "",
                "responses": {
                    "200": {
                        "description": "OK",
                        "content": {
                            "application/json": {
                                "schema": {},
                                "example": ""
                            }
                        }
                    },
                    "404": {
                        "description": "Not Found",
                        "content": {
                            "application/json": {
                                "schema": {},
                                "example": ""
                            }
                        }
                    },
                    "500": {
                        "description": "Internal Server Error",
                        "content": {
                            "application/json": {
                                "schema": {},
                                "example": ""
                            }
                        }
                    }
                },
                "tags": [
                    "Gestion des produits"
                ],
                "parameters": [
                    {
                        "in": "header",
                        "name": "User-Agent",
                        "type": "string"
                    }
                ],
                "requestBody": {
                    "content": {
                        "application/x-www-form-urlencoded": {
                            "schema": {
                                "type": "object",
                                "properties": {
                                    "categorie_id": {
                                        "type": "integer"
                                    },
                                    "image": {
                                        "type": "string"
                                    },
                                    "description": {
                                        "type": "string"
                                    },
                                    "prix": {
                                        "type": "integer"
                                    },
                                    "quantite": {
                                        "type": "integer"
                                    },
                                    "reference": {
                                        "type": "string"
                                    }
                                }
                            },
                            "example": {
                                "categorie_id": 2,
                                "image": "chemin/vers/image.jpg",
                                "description": "Description huile",
                                "prix": 19.99,
                                "quantite": 50,
                                "reference": "PROD12349"
                            }
                        }
                    }
                }
            }
        },
        "/api/categories": {
            "get": {
                "summary": "Afficher la liste",
                "description": "",
                "responses": {
                    "200": {
                        "description": "OK",
                        "content": {
                            "application/json": {
                                "schema": {},
                                "example": ""
                            }
                        }
                    },
                    "404": {
                        "description": "Not Found",
                        "content": {
                            "application/json": {
                                "schema": {},
                                "example": ""
                            }
                        }
                    },
                    "500": {
                        "description": "Internal Server Error",
                        "content": {
                            "application/json": {
                                "schema": {},
                                "example": ""
                            }
                        }
                    }
                },
                "tags": [
                    "Gestion des categories"
                ],
                "parameters": [
                    {
                        "in": "header",
                        "name": "User-Agent",
                        "type": "string"
                    }
                ]
            },
            "post": {
                "summary": "Ajouter",
                "description": "",
                "responses": {
                    "201": {
                        "description": "Created successfully",
                        "content": {
                            "application/json": {
                                "schema": {},
                                "example": ""
                            }
                        }
                    },
                    "400": {
                        "description": "Bad Request",
                        "content": {
                            "application/json": {
                                "schema": {},
                                "example": ""
                            }
                        }
                    },
                    "401": {
                        "description": "Unauthorized",
                        "content": {
                            "application/json": {
                                "schema": {},
                                "example": ""
                            }
                        }
                    },
                    "403": {
                        "description": "Forbidden",
                        "content": {
                            "application/json": {
                                "schema": {},
                                "example": ""
                            }
                        }
                    }
                },
                "tags": [
                    "Gestion des categories"
                ],
                "parameters": [
                    {
                        "in": "header",
                        "name": "User-Agent",
                        "type": "string"
                    }
                ],
                "requestBody": {
                    "content": {
                        "multipart/form-data": {
                            "schema": {
                                "type": "object",
                                "properties": {
                                    "nom_complet": {
                                        "type": "string"
                                    },
                                    "description": {
                                        "type": "string"
                                    }
                                }
                            },
                            "example": {
                                "nom_complet": "tomate",
                                "description": "Description de la catgorie laitlaitcaille"
                            }
                        }
                    }
                }
            }
        },
        "/api/categories/1": {
            "get": {
                "summary": "Voir detail",
                "description": "",
                "responses": {
                    "200": {
                        "description": "OK",
                        "content": {
                            "application/json": {
                                "schema": {},
                                "example": ""
                            }
                        }
                    },
                    "404": {
                        "description": "Not Found",
                        "content": {
                            "application/json": {
                                "schema": {},
                                "example": ""
                            }
                        }
                    },
                    "500": {
                        "description": "Internal Server Error",
                        "content": {
                            "application/json": {
                                "schema": {},
                                "example": ""
                            }
                        }
                    }
                },
                "tags": [
                    "Gestion des categories"
                ],
                "parameters": [
                    {
                        "in": "header",
                        "name": "User-Agent",
                        "type": "string"
                    }
                ]
            }
        },
        "/api/categories/6": {
            "delete": {
                "summary": "Supprimer",
                "description": "",
                "responses": {
                    "204": {
                        "description": "Deleted successfully",
                        "content": {
                            "application/json": {
                                "schema": {},
                                "example": ""
                            }
                        }
                    },
                    "401": {
                        "description": "Unauthorized",
                        "content": {
                            "application/json": {
                                "schema": {},
                                "example": ""
                            }
                        }
                    },
                    "403": {
                        "description": "Forbidden",
                        "content": {
                            "application/json": {
                                "schema": {},
                                "example": ""
                            }
                        }
                    },
                    "404": {
                        "description": "Not Found",
                        "content": {
                            "application/json": {
                                "schema": {},
                                "example": ""
                            }
                        }
                    }
                },
                "tags": [
                    "Gestion des categories"
                ],
                "parameters": [
                    {
                        "in": "header",
                        "name": "User-Agent",
                        "type": "string"
                    }
                ]
            }
        },
        "/api/categories/2": {
            "patch": {
                "summary": "Modifier",
                "description": "",
                "responses": {
                    "200": {
                        "description": "OK",
                        "content": {
                            "application/json": {
                                "schema": {},
                                "example": ""
                            }
                        }
                    },
                    "404": {
                        "description": "Not Found",
                        "content": {
                            "application/json": {
                                "schema": {},
                                "example": ""
                            }
                        }
                    },
                    "500": {
                        "description": "Internal Server Error",
                        "content": {
                            "application/json": {
                                "schema": {},
                                "example": ""
                            }
                        }
                    }
                },
                "tags": [
                    "Gestion des categories"
                ],
                "parameters": [
                    {
                        "in": "header",
                        "name": "User-Agent",
                        "type": "string"
                    }
                ],
                "requestBody": {
                    "content": {
                        "application/x-www-form-urlencoded": {
                            "schema": {
                                "type": "object",
                                "properties": {
                                    "nom_complet": {
                                        "type": "string"
                                    },
                                    "description": {
                                        "type": "string"
                                    }
                                }
                            },
                            "example": {
                                "nom_complet": "Catgorie porie",
                                "description": "Nouvelle description pour la catgorie A"
                            }
                        }
                    }
                }
            }
        },
        "/api/register": {
            "post": {
                "summary": "Register",
                "description": "",
                "responses": {
                    "201": {
                        "description": "Created successfully",
                        "content": {
                            "application/json": {
                                "schema": {},
                                "example": ""
                            }
                        }
                    },
                    "400": {
                        "description": "Bad Request",
                        "content": {
                            "application/json": {
                                "schema": {},
                                "example": ""
                            }
                        }
                    },
                    "401": {
                        "description": "Unauthorized",
                        "content": {
                            "application/json": {
                                "schema": {},
                                "example": ""
                            }
                        }
                    },
                    "403": {
                        "description": "Forbidden",
                        "content": {
                            "application/json": {
                                "schema": {},
                                "example": ""
                            }
                        }
                    }
                },
                "tags": [
                    "Authentification"
                ],
                "parameters": [
                    {
                        "in": "header",
                        "name": "User-Agent",
                        "type": "string"
                    }
                ],
                "requestBody": {
                    "content": {
                        "multipart/form-data": {
                            "schema": {
                                "type": "object",
                                "properties": {
                                    "nom_complet": {
                                        "type": "string"
                                    },
                                    "telephone": {
                                        "type": "string"
                                    },
                                    "email": {
                                        "type": "string"
                                    },
                                    "password": {
                                        "type": "string"
                                    },
                                    "password_confirmation": {
                                        "type": "string"
                                    }
                                }
                            },
                            "example": {
                                "nom_complet": "bassine niang",
                                "telephone": "771065156",
                                "email": "bassinen13@gmail.com",
                                "password": "nessiba96",
                                "password_confirmation": "nessiba96"
                            }
                        }
                    }
                }
            }
        },
        "/api/login": {
            "post": {
                "summary": "Login client",
                "description": "",
                "responses": {
                    "201": {
                        "description": "Created successfully",
                        "content": {
                            "application/json": {
                                "schema": {},
                                "example": ""
                            }
                        }
                    },
                    "400": {
                        "description": "Bad Request",
                        "content": {
                            "application/json": {
                                "schema": {},
                                "example": ""
                            }
                        }
                    },
                    "401": {
                        "description": "Unauthorized",
                        "content": {
                            "application/json": {
                                "schema": {},
                                "example": ""
                            }
                        }
                    },
                    "403": {
                        "description": "Forbidden",
                        "content": {
                            "application/json": {
                                "schema": {},
                                "example": ""
                            }
                        }
                    }
                },
                "tags": [
                    "Authentification"
                ],
                "parameters": [
                    {
                        "in": "header",
                        "name": "User-Agent",
                        "type": "string"
                    }
                ],
                "requestBody": {
                    "content": {
                        "multipart/form-data": {
                            "schema": {
                                "type": "object",
                                "properties": {
                                    "email": {
                                        "type": "string"
                                    },
                                    "password": {
                                        "type": "string"
                                    }
                                }
                            },
                            "example": {
                                "email": "bassinen13@gmail.com",
                                "password": "nessiba96"
                            }
                        }
                    }
                }
            }
        },
        "/api/logout": {
            "post": {
                "summary": "logout",
                "description": "",
                "responses": {
                    "201": {
                        "description": "Created successfully",
                        "content": {
                            "application/json": {
                                "schema": {},
                                "example": ""
                            }
                        }
                    },
                    "400": {
                        "description": "Bad Request",
                        "content": {
                            "application/json": {
                                "schema": {},
                                "example": ""
                            }
                        }
                    },
                    "401": {
                        "description": "Unauthorized",
                        "content": {
                            "application/json": {
                                "schema": {},
                                "example": ""
                            }
                        }
                    },
                    "403": {
                        "description": "Forbidden",
                        "content": {
                            "application/json": {
                                "schema": {},
                                "example": ""
                            }
                        }
                    }
                },
                "tags": [
                    "Authentification"
                ],
                "parameters": [
                    {
                        "in": "header",
                        "name": "User-Agent",
                        "type": "string"
                    }
                ]
            }
        }
    }
}